spydi/__init__.py
spydi/context.py
spydi/exception.py
spydi/factory.py
spydi/instance_holder.py
spydi/tuple_destructuring.py
spy_di-0.4.0.dist-info/LICENSE
spy_di-0.4.0.dist-info/METADATA
spy_di-0.4.0.dist-info/WHEEL
spy_di-0.4.0.dist-info/top_level.txt
spy_di-0.4.0.dist-info/RECORD
