Metadata-Version: 2.1
Name: spy-di
Version: 0.4.0
Summary: A Simple PYthon Dependency Injection Library
Home-page: https://gitlab.com/madmax_inc/spydi
Author: Maksim Penkov
Author-email: me@madmax.im
License: UNKNOWN
Keywords: dependency-injection di
Platform: UNKNOWN
Classifier: Programming Language :: Python :: 3
Classifier: License :: OSI Approved :: Apache Software License
Classifier: Operating System :: OS Independent
Requires-Python: >=3.6
